echocodepackage/__init__.py
echocodepackage-0.1.dist-info/licenses/LICENSE.txt
echocodepackage-0.1.dist-info/METADATA
echocodepackage-0.1.dist-info/WHEEL
echocodepackage-0.1.dist-info/top_level.txt
echocodepackage-0.1.dist-info/RECORD
